redisdb/backends.py
redisdb/models.py
redisdb/__init__.py
redisdb/compat.py
django_redisdb-0.2.1.dist-info/top_level.txt
django_redisdb-0.2.1.dist-info/METADATA
django_redisdb-0.2.1.dist-info/DESCRIPTION.rst
django_redisdb-0.2.1.dist-info/metadata.json
django_redisdb-0.2.1.dist-info/WHEEL
django_redisdb-0.2.1.dist-info/RECORD
