Metadata-Version: 2.0
Name: django-redisdb
Version: 0.2.1
Summary: Django redis backend
Home-page: http://django-redisdb.readthedocs.org
Author: Jakub STOLARSKI (Dryobates)
Author-email: jakub.stolarski@kidosoft.pl
License: beerware
Keywords: django redis
Platform: UNKNOWN
Classifier: Development Status :: 4 - Beta
Classifier: Intended Audience :: Developers
Classifier: License :: OSI Approved :: BSD License
Classifier: Operating System :: OS Independent
Classifier: Environment :: Web Environment
Classifier: Framework :: Django
Classifier: Topic :: Software Development :: Libraries :: Python Modules
Classifier: Programming Language :: Python
Classifier: Programming Language :: Python :: 2
Classifier: Programming Language :: Python :: 2.7
Classifier: Programming Language :: Python :: 3
Classifier: Programming Language :: Python :: 3.2
Classifier: Programming Language :: Python :: 3.3
Classifier: Programming Language :: Python :: 3.4
Requires-Dist: redis
Requires-Dist: hash-ring
Requires-Dist: Django (>=1.2)
